spikeforestwidgets/__init__.py
spikeforestwidgets/dist/33a752211d05af6684e26ec63c2ed965.gif
spikeforestwidgets/dist/792dcd18baf5f544aabcad1883d673c2.svg
spikeforestwidgets/dist/a770b6797b68e3f8920e473eb824bac0.gif
spikeforestwidgets/dist/bc7c4a59f924cf037aad6e1f9edba366.eot
spikeforestwidgets/dist/eceddf474df95d8d4a7e316668c3be85.ttf
spikeforestwidgets/dist/main.js
spikeforestwidgets-0.1.4.dist-info/METADATA
spikeforestwidgets-0.1.4.dist-info/RECORD
spikeforestwidgets-0.1.4.dist-info/WHEEL
spikeforestwidgets-0.1.4.dist-info/top_level.txt
