Metadata-Version: 2.1
Name: spikeforestwidgets
Version: 0.1.4
Summary: UNKNOWN
Home-page: https://github.com/magland/spikeforestwidgets
Author: Jeremy Magland
Author-email: jmagland@flatironinstitute.org
License: UNKNOWN
Platform: UNKNOWN
Classifier: Programming Language :: Python :: 3
Classifier: License :: OSI Approved :: Apache Software License
Classifier: Operating System :: OS Independent
Requires-Dist: ipywidgets
Requires-Dist: jp-proxy-widget
